rank_files/__init__.py
rank_files/algos.py
rank_files/cache.py
rank_files/cli.py
rank_files/document.py
rank_files/ranker.py
rank_files/prompts/pairwise-system.txt
rank_files-0.1.0.dist-info/METADATA
rank_files-0.1.0.dist-info/WHEEL
rank_files-0.1.0.dist-info/entry_points.txt
rank_files-0.1.0.dist-info/licenses/LICENSE
rank_files-0.1.0.dist-info/RECORD
