Metadata-Version: 2.4
Name: rank-files
Version: 0.1.0
Summary: Add your description here
Author-email: Jacob Williams <jacobaw@gmail.com>
License-File: LICENSE
Requires-Python: >=3.13.2
Requires-Dist: anthropic>=0.49.0
Requires-Dist: hypothesis>=6.131.0
Requires-Dist: ollama>=0.4.7
Requires-Dist: pytest>=8.3.5
Requires-Dist: tqdm>=4.67.1
